ciga/__init__.py
ciga/ciga.py
ciga/analysis/__init__.py
ciga/analysis/graph_centrality_analysis.py
ciga/analysis/graph_community_analysis.py
ciga/analysis/graph_properties.py
ciga/analysis/tgraph_centrality_analysis.py
ciga/analysis/tgraph_community_analysis.py
ciga/analysis/tgraph_properties.py
ciga/examples/__init__.py
ciga/examples/analysis.py
ciga/examples/centrality_analysis.py
ciga/examples/community_detection.py
ciga/examples/graph_viz.py
ciga/examples/infer_listeners.py
ciga/examples/non_acc_centrality_analysis.py
ciga/examples/tgraph_viz.py
ciga/utils/__init__.py
ciga/utils/data_utils.py
ciga/utils/graph_utils.py
ciga/visualization/__init__.py
ciga/visualization/graph_plotter.py
ciga-0.1.0.dist-info/licenses/LICENSE
ciga-0.1.0.dist-info/METADATA
ciga-0.1.0.dist-info/WHEEL
ciga-0.1.0.dist-info/top_level.txt
ciga-0.1.0.dist-info/RECORD
