Metadata-Version: 2.4
Name: ciga
Version: 0.1.0
Summary: Character interaction temporal graph analysis
Home-page: https://github.com/MediaCompLab/CIGA
Author: Media Comprehension Lab
Author-email: shu13@gsu.edu
Classifier: Programming Language :: Python :: 3
Classifier: License :: OSI Approved :: GNU General Public License v3 (GPLv3)
Classifier: Operating System :: OS Independent
Requires-Python: >=3.6
License-File: LICENSE
Requires-Dist: pandas
Requires-Dist: igraph
Requires-Dist: numpy
Requires-Dist: tqdm
Requires-Dist: matplotlib
Provides-Extra: all
Requires-Dist: anthropic; extra == "all"
Requires-Dist: openai; extra == "all"
Requires-Dist: pyvis>=0.3.0; extra == "all"
Provides-Extra: dev
Requires-Dist: pytest>=7.0; extra == "dev"
Requires-Dist: twine>=4.0.2; extra == "dev"
Provides-Extra: visualization
Requires-Dist: pyvis>=0.3.0; extra == "visualization"
Dynamic: author
Dynamic: author-email
Dynamic: classifier
Dynamic: description
Dynamic: description-content-type
Dynamic: home-page
Dynamic: license-file
Dynamic: provides-extra
Dynamic: requires-dist
Dynamic: requires-python
Dynamic: summary
